CHANGES.rst
HOWTO.rst
LICENSE
MANIFEST.in
README.rst
setup.py
tslist/__init__.py
tslist/api.py
tslist/parser.py
tslist/tree.py
tslist/ts.py
tslist/tsclient.py
tslist/tsdict.py
tslist/tsdiff.py
tslist/tsdir.py
tslist/tslist.py
tslist/tsobj.py
tslist.egg-info/PKG-INFO
tslist.egg-info/SOURCES.txt
tslist.egg-info/dependency_links.txt
tslist.egg-info/top_level.txt