Metadata-Version: 2.1
Name: tslist
Version: 0.3.4
Summary: timestamp with a list (created by auxilium)
Home-page: https://github.com/sonntagsgesicht/tslist
Author: sonntagsgesicht
Author-email: sonntagsgesicht@icloud.com
License: Apache License 2.0
Platform: any
Classifier: Development Status :: 3 - Alpha
Classifier: Intended Audience :: Education
Classifier: Intended Audience :: Developers
Classifier: License :: OSI Approved :: Apache Software License
Classifier: Operating System :: OS Independent
Classifier: Programming Language :: Python
Classifier: Programming Language :: Python :: 3
Classifier: Programming Language :: Python :: 3.10
Classifier: Programming Language :: Python :: 3.11
Classifier: Programming Language :: Python :: 3.12
Classifier: Programming Language :: Python :: 3.13
Classifier: Topic :: Education
Classifier: Topic :: Software Development
License-File: LICENSE
